{
   "pokemon" :  [
       {
           "name" : "Treecko",
           "number" : "252",
           "sprite" : "https://raw.githubusercontent.com/PokeAPI/sprites/master/sprites/pokemon/252.png",
           "color" : "rgb(255, 196, 196)",
           "type" : [
                "grass"
              
           ],
           "height" : "1' 08\"",
           "weight" : "11.0 lbs",
           "abilities" : [
               "Overgrow",
               "Chlorophyll"
           ],
           "stats" : {
               "hp" : 50,
               "attack" : 49,
               "defense" : 65,
               "sp.atk" : 49,
               "sp.def" : 65,
               "speed" : 45,
               "total" : 318
           },
            "evolution" : [
                "Treecko",
                "Grovyle",
                "Sceptile"
              ]
       },
       {
           "name" : "Grovyle",
           "number" : "253",
           "sprite" : "https://raw.githubusercontent.com/PokeAPI/sprites/master/sprites/pokemon/253.png",
           "color" : "rgb(255, 196, 196)",
           "type" : [
                "grass"             
           ],
           "height" : "2' 11\"",
           "weight" : "47.6 lbs",
           "abilities" : [
               "Overgrow",
               "Chlorophyll"
           ],
           "stats" : {
            "hp" : 60,
            "attack" : 79,
            "defense" : 85,
            "sp.atk" : 79,
            "sp.def" : 85,
            "speed" : 60,
            "total" : 405
           },
            "evolution" : [
                "Treecko",
                "Grovyle",
                "Sceptile"
              ]
         },
         {
             "name" : "Sceptile",
             "number" : "254",
             "sprite" : "https://raw.githubusercontent.com/PokeAPI/sprites/master/sprites/pokemon/254.png",
             "color" : "rgb(255, 196, 196)",
             "type" : [
                  "grass"             
             ],
             "height" : "5' 07\"",
             "weight" : "115.1 lbs",
             "abilities" : [
                 "Overgrow",
                 "Chlorophyll"
             ],
             "stats" : {
                "hp" : 70,
                "attack" : 85,
                "defense" : 65,
                "sp.atk" : 105,
                "sp.def" : 85,
                "speed" : 120,
                "total" : 530
             },
              "evolution" : [
                  "Treecko",
                  "Grovyle",
                  "Sceptile"
                ]
        },
        {
            "name" : "Torchic",
            "number" : "255",
            "sprite" : "https://raw.githubusercontent.com/PokeAPI/sprites/master/sprites/pokemon/255.png",
            "color" : "rgb(255, 196, 196)",
            "type" : [
                 "fire"             
            ],
            "height" : "1' 04\"",
            "weight" : "5.5 lbs",
            "abilities" : [
                "Blaze",
                "Speed Boost"
            ],
            "stats" : {
                "hp" : 45,
                "attack" : 60,
                "defense" : 40,
                "sp.atk" : 70,
                "sp.def" : 50,
                "speed" : 45,
                "total" : 300
            },
             "evolution" : [
                 "Torchic",
                 "Combusken",
                 "Blaziken"
               ]
        },
        {
            "name" : "Combusken",
            "number" : "256",
            "sprite" : "https://raw.githubusercontent.com/PokeAPI/sprites/master/sprites/pokemon/256.png",
            "color" : "rgb(255, 196, 196)",
            "type" : [
                 "fire",
                 "fighting"             
            ],
            "height" : "2' 11\"",
            "weight" : "43.0 lbs",
            "abilities" : [
                "Blaze",
                "Speed Boost"
            ],
            "stats" : {
                "hp" : 60,
                "attack" : 85,
                "defense" : 60,
                "sp.atk" : 85,
                "sp.def" : 60,
                "speed" : 55,
                "total" : 405
            },
             "evolution" : [
                 "Torchic",
                 "Combusken",
                 "Blaziken"
               ]
        },
        {
            "name" : "Blaziken",
            "number" : "257",
            "sprite" : "https://raw.githubusercontent.com/PokeAPI/sprites/master/sprites/pokemon/257.png",
            "color" : "rgb(255, 196, 196)",
            "type" : [
                 "fire",
                 "fighting"             
            ],
            "height" : "6' 03\"",
            "weight" : "114.6 lbs",
            "abilities" : [
                "Blaze",
                "Speed Boost"
            ],
            "stats" : {
                "hp" : 70,
                "attack" : 115,
                "defense" : 70,
                "sp.atk" : 115,
                "sp.def" : 70,
                "speed" : 80,
                "total" : 530
            },
             "evolution" : [
                 "Torchic",
                 "Combusken",
                 "Blaziken"
               ]

        },
        {
            "name" : "Mudkip",
            "number" : "258",
            "sprite" : "https://raw.githubusercontent.com/PokeAPI/sprites/master/sprites/pokemon/258.png",
            "color" : "rgb(255, 196, 196)",
            "type" : [
                 "water"             
            ],
            "height" : "1' 04\"",
            "weight" : "16.8 lbs",
            "abilities" : [
                "Torrent",
                "Damp"
            ],
            "stats" : {
                "hp" : 50,
                "attack" : 70,
                "defense" : 50,
                "sp.atk" : 50,
                "sp.def" : 50,
                "speed" : 40,
                "total" : 300
            },
             "evolution" : [
                 "Mudkip",
                 "Marshtomp",
                 "Swampert"
               ]

        },
        {
            "name" : "Marshtomp",
            "number" : "259",
            "sprite" : "https://raw.githubusercontent.com/PokeAPI/sprites/master/sprites/pokemon/259.png",
            "color" : "rgb(255, 196, 196)",
            "type" : [
                 "water",
                 "ground"             
            ],
            "height" : "2' 04\"",
            "weight" : "61.7 lbs",
            "abilities" : [
                "Torrent",
                "Damp"
            ],
            "stats" : {
                "hp" : 70,
                "attack" : 85,
                "defense" : 70,
                "sp.atk" : 60,
                "sp.def" : 70,
                "speed" : 50,
                "total" : 405
            },
             "evolution" : [
                 "Mudkip",
                 "Marshtomp",
                 "Swampert"
               ]

        },
        {
            "name"  : "Swampert",
            "number" : "260",
            "sprite" : "https://raw.githubusercontent.com/PokeAPI/sprites/master/sprites/pokemon/260.png",
            "color" : "rgb(255, 196, 196)",
            "type" : [
                 "water",
                 "ground"             
            ],
            "height" : "4' 11\"",
            "weight" : "180.6 lbs",
            "abilities" : [
                "Torrent",
                "Damp"
            ],
            "stats" : {
                "hp" : 90,
                "attack" : 115,
                "defense" : 90,
                "sp.atk" : 85,
                "sp.def" : 90,
                "speed" : 60,
                "total" : 540
            },
             "evolution" : [
                 "Mudkip",
                 "Marshtomp",
                 "Swampert"
               ]

        },
        {
            "name" : "Poochyena",
            "number" : "261",
            "sprite" : "https://raw.githubusercontent.com/PokeAPI/sprites/master/sprites/pokemon/261.png",
            "color" : "rgb(255, 196, 196)",
            "type" : [
                 "dark"             
            ],
            "height" : "1' 08\"",
            "weight" : "30.0 lbs",
            "abilities" : [
                "Run Away",
                "Quick Feet"
            ],
            "stats" : {
                "hp" : 35,
                "attack" : 55,
                "defense" : 35,
                "sp.atk" : 30,
                "sp.def" : 30,
                "speed" : 35,
                "total" : 220
            },
             "evolution" : [
                 "Poochyena",
                 "Mightyena"
               ]

        },
        {
            "name" : "Mightyena",
            "number" : "262",
            "sprite" : "https://raw.githubusercontent.com/PokeAPI/sprites/master/sprites/pokemon/262.png",
            "color" : "rgb(255, 196, 196)",
            "type" : [
                 "dark"             
            ],
            "height" : "3' 03\"",
            "weight" : "81.6 lbs",
            "abilities" : [
                "Intimidate",
                "Quick Feet"
            ],
            "stats" : {
                "hp" : 60,
                "attack" : 90,
                "defense" : 70,
                "sp.atk" : 60,
                "sp.def" : 60,
                "speed" : 55,
                "total" : 405
            },
             "evolution" : [
                 "Poochyena",
                 "Mightyena"
               ]

        },
        {
            "name" : "Zigzagoon",
            "number" : "263",
            "sprite" : "https://raw.githubusercontent.com/PokeAPI/sprites/master/sprites/pokemon/263.png",
            "color" : "rgb(255, 196, 196)",
            "type" : [
                 "normal"             
            ],
            "height" : "1' 04\"",
            "weight" : "38.6 lbs",
            "abilities" : [
                "Pickup",
                "Gluttony"
            ],
            "stats" : {
                "hp" : 38,
                "attack" : 30,
                "defense" : 41,
                "sp.atk" : 30,
                "sp.def" : 41,
                "speed" : 60,
                "total" : 300
            },
             "evolution" : [
                 "Zigzagoon",
                 "Linoone"
               ]

        },
        {
            "name" : "Linoone",
            "number" : "264",
            "sprite" : "https://raw.githubusercontent.com/PokeAPI/sprites/master/sprites/pokemon/264.png",
            "color" : "rgb(255, 196, 196)",
            "type" : [
                 "normal"             
            ],
            "height" : "1' 08\"",
            "weight" : "71.7 lbs",
            "abilities" : [
                "Pickup",
                "Gluttony"
            ],
            "stats" : {
                "hp" : 68,
                "attack" : 70,
                "defense" : 61,
                "sp.atk" : 50,
                "sp.def" : 61,
                "speed" : 100,
                "total" : 460
            },
             "evolution" : [
                 "Zigzagoon",
                 "Linoone"
               ]

        },
        {
            "name" : "Wurmple",
            "number" : "265",
            "sprite" : "https://raw.githubusercontent.com/PokeAPI/sprites/master/sprites/pokemon/265.png",
            "color" : "rgb(255, 196, 196)",
            "type" : [
                 "bug"             
            ],
            "height" : "1' 00\"",
            "weight" : "7.9 lbs",
            "abilities" : [
                "Shield Dust",
                "Run Away"
            ],
            "stats" : {
                "hp" : 45,
                "attack" : 35,
                "defense" : 55,
                "sp.atk" : 25,
                "sp.def" : 25,
                "speed" : 15,
                "total" : 250
            },
             "evolution" : [
                 "Wurmple",
                 "Silcoon",
                 "Cascoon",
                 "Beautifly",
                 "Dustox"
               ]

        },
        {
            "name" : "Silcoon",
            "number" : "266",
            "sprite" : "https://raw.githubusercontent.com/PokeAPI/sprites/master/sprites/pokemon/266.png",
            "color" : "rgb(255, 196, 196)",
            "type" : [
                 "bug"             
            ],
            "height" : "2' 00\"",
            "weight" : "22.0 lbs",
            "abilities" : [
                "Shed Skin",
                "Run Away"
            ],
            "stats" : {
                "hp" : 50,
                "attack" : 35,
                "defense" : 55,
                "sp.atk" : 25,
                "sp.def" : 25,
                "speed" : 15,
                "total" : 300
            },
             "evolution" : [
                 "Wurmple",
                 "Silcoon",
                 "Cascoon",
                 "Beautifly",
                 "Dustox"
               ]

        },
        {
            "name" : "Beautifly",
            "number" : "267",
            "sprite" : "https://raw.githubusercontent.com/PokeAPI/sprites/master/sprites/pokemon/267.png",
            "color" : "rgb(255, 196, 196)",
            "type" : [
                 "bug",
                 "flying"             
            ],
            "height" : "3' 03\"",
            "weight" : "62.6 lbs",
            "abilities" : [
                "Swarm",
                "Rivalry"
            ],
            "stats" : {
                "hp" : 60,
                "attack" : 70,
                "defense" : 50,
                "sp.atk" : 100,
                "sp.def" : 50,
                "speed" : 65,
                "total" : 455
            },
             "evolution" : [
                 "Wurmple",
                 "Silcoon",
                 "Cascoon",
                 "Beautifly",
                 "Dustox"
               ]

        },
        {
            "name" : "Cascoon",
            "number" : "268",
            "sprite" : "https://raw.githubusercontent.com/PokeAPI/sprites/master/sprites/pokemon/268.png",
            "color" : "rgb(255, 196, 196)",
            "type" : [
                 "bug"             
            ],
            "height" : "2' 04\"",
            "weight" : "25.4 lbs",
            "abilities" : [
                "Shed Skin",
                "Sticky Hold"
            ],
            "stats" : {
                "hp" : 50,
                "attack" : 35,
                "defense" : 55,
                "sp.atk" : 25,
                "sp.def" : 25,
                "speed" : 15,
                "total" : 300
            },
             "evolution" : [
                 "Wurmple",
                 "Silcoon",
                 "Cascoon",
                 "Beautifly",
                 "Dustox"
               ]

        },
        {
            "name" : "Dustox",
            "number" : "269",
            "sprite" : "https://raw.githubusercontent.com/PokeAPI/sprites/master/sprites/pokemon/269.png",
            "color" : "rgb(255, 196, 196)",
            "type" : [
                 "bug",
                 "poison"             
            ],
            "height" : "3' 11\"",
            "weight" : "69.7 lbs",
            "abilities" : [
                "Shield Dust",
                "Compound Eyes"
            ],
            "stats" : {
                "hp" : 60,
                "attack" : 55,
                "defense" : 50,
                "sp.atk" : 90,
                "sp.def" : 80,
                "speed" : 70,
                "total" : 455
            },
             "evolution" : [
                 "Wurmple",
                 "Silcoon",
                 "Cascoon",
                 "Beautifly",
                 "Dustox"
               ]

        },
        {
            "name" : "Lotad",
            "number" : "270",
            "sprite" : "https://raw.githubusercontent.com/PokeAPI/sprites/master/sprites/pokemon/270.png",
            "color" : "rgb(255, 196, 196)",
            "type" : [
                 "water",
                 "grass"             
            ],
            "height" : "1' 08\"",
            "weight" : "5.7 lbs",
            "abilities" : [
                "Swift Swim",
                "Rain Dish"
            ],
            "stats" : {
                "hp" : 40,
                "attack" : 30,
                "defense" : 30,
                "sp.atk" : 40,
                "sp.def" : 50,
                "speed" : 30,
                "total" : 280
            },
             "evolution" : [
                 "Lotad",
                 "Lombre",
                 "Ludicolo"
               ]

        },
        {
            "name" : "Lombre",
            "number" : "271",
            "sprite" : "https://raw.githubusercontent.com/PokeAPI/sprites/master/sprites/pokemon/271.png",
            "color" : "rgb(255, 196, 196)",
            "type" : [
                 "water",
                 "grass"             
            ],
            "height" : "3' 11\"",
            "weight" : "71.7 lbs",
            "abilities" : [
                "Swift Swim",
                "Rain Dish"
            ],
            "stats" : {
                "hp" : 60,
                "attack" : 50,
                "defense" : 50,
                "sp.atk" : 60,
                "sp.def" : 70,
                "speed" : 50,
                "total" : 380
            },
             "evolution" : [
                 "Lotad",
                 "Lombre",
                 "Ludicolo"
               ]

        },
        {
            "name" : "Ludicolo",
            "number" : "272",
            "sprite" : "https://raw.githubusercontent.com/PokeAPI/sprites/master/sprites/pokemon/272.png",
            "color" : "rgb(255, 196, 196)",
            "type" : [
                 "water",
                 "grass"             
            ],
            "height" : "4' 11\"",
            "weight" : "121.3 lbs",
            "abilities" : [
                "Swift Swim",
                "Rain Dish"
            ],
            "stats" : {
                "hp" : 80,
                "attack" : 70,
                "defense" : 70,
                "sp.atk" : 90,
                "sp.def" : 100,
                "speed" : 70,
                "total" : 490
            },
             "evolution" : [
                 "Lotad",
                 "Lombre",
                 "Ludicolo"
               ]
        },
        {
            "name" : "Seedot",
            "number" : "273",
            "sprite" : "https://raw.githubusercontent.com/PokeAPI/sprites/master/sprites/pokemon/273.png",
            "color" : "rgb(255, 196, 196)",
            "type" : [
                 "grass"             
            ],
            "height" : "1' 08\"",
            "weight" : "8.8 lbs",
            "abilities" : [
                "Chlorophyll",
                "Early Bird"
            ],
            "stats" : {
                "hp" : 40,
                "attack" : 40,
                "defense" : 50,
                "sp.atk" : 30,
                "sp.def" : 30,
                "speed" : 30,
                "total" : 280
            },
             "evolution" : [
                 "Seedot",
                 "Nuzleaf",
                 "Shiftry"
               ]

        },
        {
            "name" : "Nuzleaf",
            "number" : "274",
            "sprite" : "https://raw.githubusercontent.com/PokeAPI/sprites/master/sprites/pokemon/274.png",
            "color" : "rgb(255, 196, 196)",
            "type" : [
                 "grass",
                 "dark"             
            ],
            "height" : "3' 03\"",
            "weight" : "61.7 lbs",
            "abilities" : [
                "Chlorophyll",
                "Early Bird"
            ],
            "stats" : {
                "hp" : 70,
                "attack" : 70,
                "defense" : 40,
                "sp.atk" : 60,
                "sp.def" : 40,
                "speed" : 60,
                "total" : 380
            },
             "evolution" : [
                 "Seedot",
                 "Nuzleaf",
                 "Shiftry"
               ]

        },
        {
            "name" : "Shiftry",
            "number" : "275",
            "sprite" : "https://raw.githubusercontent.com/PokeAPI/sprites/master/sprites/pokemon/275.png",
            "color" : "rgb(255, 196, 196)",
            "type" : [
                 "grass",
                 "dark"             
            ],
            "height" : "4' 03\"",
            "weight" : "131.4 lbs",
            "abilities" : [
                "Chlorophyll",
                "Early Bird"
            ],
            "stats" : {
                "hp" : 90,
                "attack" : 100,
                "defense" : 60,
                "sp.atk" : 90,
                "sp.def" : 60,
                "speed" : 80,
                "total" : 490
            },
             "evolution" : [
                 "Seedot",
                 "Nuzleaf",
                 "Shiftry"
               ]

        },
        {
            "name" : "Taillow",
            "number" : "276",
            "sprite" : "https://raw.githubusercontent.com/PokeAPI/sprites/master/sprites/pokemon/276.png",
            "color" : "rgb(255, 196, 196)",
            "type" : [
                 "normal",
                 "flying"             
            ],
            "height" : "1' 00\"",
            "weight" : "5.1 lbs",
            "abilities" : [
                "Guts",
                "Scrappy"
            ],
            "stats" : {
                "hp" : 40,
                "attack" : 55,
                "defense" : 30,
                "sp.atk" : 30,
                "sp.def" : 30,
                "speed" : 85,
                "total" : 265
            },
             "evolution" : [
                 "Taillow",
                 "Swellow"
               ]

        },
        {
            "name" : "Swellow",
            "number" : "277",
            "sprite" : "https://raw.githubusercontent.com/PokeAPI/sprites/master/sprites/pokemon/277.png",
            "color" : "rgb(255, 196, 196)",
            "type" : [
                 "normal",
                 "flying"             
            ],
            "height" : "2' 04\"",
            "weight" : "43.7 lbs",
            "abilities" : [
                "Guts",
                "Scrappy"
            ],
            "stats" : {
                "hp" : 60,
                "attack" : 85,
                "defense" : 60,
                "sp.atk" : 75,
                "sp.def" : 50,
                "speed" : 125,
                "total" : 435
            },
             "evolution" : [
                 "Taillow",
                 "Swellow"
               ]

        },
        {
            "name" : "Wingull",
            "number" : "278",
            "sprite" : "https://raw.githubusercontent.com/PokeAPI/sprites/master/sprites/pokemon/278.png",
            "color" : "rgb(255, 196, 196)",
            "type" : [
                 "water",
                 "flying"             
            ],
            "height" : "2' 00\"",
            "weight" : "20.9 lbs",
            "abilities" : [
                "Keen Eye",
                "Hydration"
            ],
            "stats" : {
                "hp" : 40,
                "attack" : 30,
                "defense" : 30,
                "sp.atk" : 55,
                "sp.def" : 30,
                "speed" : 85,
                "total" : 295
            },
             "evolution" : [
                 "Wingull",
                 "Pelipper"
               ]
        },
        {
            "name" : "Pelipper",
            "number" : "279",
            "sprite" : "https://raw.githubusercontent.com/PokeAPI/sprites/master/sprites/pokemon/279.png",
            "color" : "rgb(255, 196, 196)",
            "type" : [
                 "water",
                 "flying"             
            ],
            "height" : "3' 11\"",
            "weight" : "61.7 lbs",
            "abilities" : [
                "Keen Eye",
                "Drizzle"
            ],
            "stats" : {
                "hp" : 60,
                "attack" : 50,
                "defense" : 100,
                "sp.atk" : 95,
                "sp.def" : 70,
                "speed" : 65,
                "total" : 455
            },
             "evolution" : [
                 "Wingull",
                 "Pelipper"
               ]
        },
        {
            "name" : "Ralts",
            "number" : "280",
            "sprite" : "https://raw.githubusercontent.com/PokeAPI/sprites/master/sprites/pokemon/280.png",
            "color" : "rgb(255, 196, 196)",
            "type" : [
                 "psychic",
                 "fairy"             
            ],
            "height" : "1' 04\"",
            "weight" : "14.7 lbs",
            "abilities" : [
                "Synchronize",
                "Trace"
            ],
            "stats" : {
                "hp" : 45,
                "attack" : 35,
                "defense" : 40,
                "sp.atk" : 35,
                "sp.def" : 55,
                "speed" : 50,
                "total" : 300
            },
             "evolution" : [
                 "Ralts",
                 "Kirlia",
                 "Gardevoir",
                 "Gallade"
               ]

        },
        {
            "name" : "Kirlia",
            "number" : "281",
            "sprite" : "https://raw.githubusercontent.com/PokeAPI/sprites/master/sprites/pokemon/281.png",
            "color" : "rgb(255, 196, 196)",
            "type" : [
                 "psychic",
                 "fairy"             
            ],
            "height" : "2' 07\"",
            "weight" : "44.5 lbs",
            "abilities" : [
                "Synchronize",
                "Trace"
            ],
            "stats" : {
                "hp" : 60,
                "attack" : 45,
                "defense" : 50,
                "sp.atk" : 45,
                "sp.def" : 70,
                "speed" : 80,
                "total" : 380
            },
             "evolution" : [
                 "Ralts",
                 "Kirlia",
                 "Gardevoir",
                 "Gallade"
               ]


        },
        {
            "name" : "Gardevoir",
            "number" : "282",
            "sprite" : "https://raw.githubusercontent.com/PokeAPI/sprites/master/sprites/pokemon/282.png",
            "color" : "rgb(255, 196, 196)",
            "type" : [
                 "psychic",
                 "fairy"             
            ],
            "height" : "5' 03\"",
            "weight" : "106.7 lbs",
            "abilities" : [
                "Synchronize",
                "Trace"
            ],
            "stats" : {
                "hp" : 68,
                "attack" : 65,
                "defense" : 65,
                "sp.atk" : 125,
                "sp.def" : 100,
                "speed" : 115,
                "total" : 520
            },
             "evolution" : [
                 "Ralts",
                 "Kirlia",
                 "Gardevoir"
               ]

        },
        {
            "name" : "Surskit",
            "number" : "283",
            "sprite" : "https://raw.githubusercontent.com/PokeAPI/sprites/master/sprites/pokemon/283.png",
            "color" : "rgb(255, 196, 196)",
            "type" : [
                 "bug",
                 "water"             
            ],
            "height" : "1' 08\"",
            "weight" : "3.7 lbs",
            "abilities" : [
                "Swift Swim",
                "Rain Dish"
            ],
            "stats" : {
                "hp" : 40,
                "attack" : 30,
                "defense" : 32,
                "sp.atk" : 50,
                "sp.def" : 52,
                "speed" : 65,
                "total" : 305
            },
             "evolution" : [
                 "Surskit",
                 "Masquerain"
               ]

        },
        {
            "name" : "Masquerain",
            "number" : "284",
            "sprite" : "https://raw.githubusercontent.com/PokeAPI/sprites/master/sprites/pokemon/284.png",
            "color" : "rgb(255, 196, 196)",
            "type" : [
                 "bug",
                 "flying"             
            ],
            "height" : "2' 07\"",
            "weight" : "7.9 lbs",
            "abilities" : [
                "Intimidate",
                "Keen Eye"
            ],
            "stats" : {
                "hp" : 70,
                "attack" : 60,
                "defense" : 62,
                "sp.atk" : 100,
                "sp.def" : 82,
                "speed" : 80,
                "total" : 495
            },
             "evolution" : [
                 "Surskit",
                 "Masquerain"
               ]
        },
        {
            "name" : "Shroomish",
            "number" : "285",
            "sprite" : "https://raw.githubusercontent.com/PokeAPI/sprites/master/sprites/pokemon/285.png",
            "color" : "rgb(255, 196, 196)",
            "type" : [
                 "grass"             
            ],
            "height" : "1' 04\"",
            "weight" : "9.9 lbs",
            "abilities" : [
                "Effect Spore",
                "Poison Heal"
            ],
            "stats" : {
                "hp" : 60,
                "attack" : 40,
                "defense" : 60,
                "sp.atk" : 40,
                "sp.def" : 60,
                "speed" : 35,
                "total" : 305
            },
             "evolution" : [
                 "Shroomish",
                 "Breloom"
               ]

        },
        {
            "name" : "Breloom",
            "number" : "286",
            "sprite" : "https://raw.githubusercontent.com/PokeAPI/sprites/master/sprites/pokemon/286.png",
            "color" : "rgb(255, 196, 196)",
            "type" : [
                 "grass",
                 "fighting"             
            ],
            "height" : "3' 11\"",
            "weight" : "86.4 lbs",
            "abilities" : [
                "Effect Spore",
                "Poison Heal"
            ],
            "stats" : {
                "hp" : 60,
                "attack" : 130,
                "defense" : 80,
                "sp.atk" : 60,
                "sp.def" : 60,
                "speed" : 70,
                "total" : 485
            },
             "evolution" : [
                 "Shroomish",
                 "Breloom"
               ]

        },
        {
            "name" : "Slakoth",
            "number" : "287",
            "sprite" : "https://raw.githubusercontent.com/PokeAPI/sprites/master/sprites/pokemon/287.png",
            "color" : "rgb(255, 196, 196)",
            "type" : [
                 "normal"             
            ],
            "height" : "2' 07\"",
            "weight" : "52.9 lbs",
            "abilities" : [
                "Truant"
            ],
            "stats" : {
                "hp" : 60,
                "attack" : 60,
                "defense" : 45,
                "sp.atk" : 35,
                "sp.def" : 35,
                "speed" : 50,
                "total" : 305
            },
             "evolution" : [
                 "Slakoth",
                 "Vigoroth",
                 "Slaking"
               ]
               
        },
        {
            "name" : "Vigoroth",
            "number" : "288",
            "sprite" : "https://raw.githubusercontent.com/PokeAPI/sprites/master/sprites/pokemon/288.png",
            "color" : "rgb(255, 196, 196)",
            "type" : [
                 "normal"             
            ],
            "height" : "4' 07\"",
            "weight" : "102.5 lbs",
            "abilities" : [
                "Vital Spirit"
            ],
            "stats" : {
                "hp" : 80,
                "attack" : 80,
                "defense" : 55,
                "sp.atk" : 60,
                "sp.def" : 55,
                "speed" : 90,
                "total" : 455
            },
             "evolution" : [
                 "Slakoth",
                 "Vigoroth",
                 "Slaking"
               ]

        },
        {
            "name" : "Slaking",
            "number" : "289",
            "sprite" : "https://raw.githubusercontent.com/PokeAPI/sprites/master/sprites/pokemon/289.png",
            "color" : "rgb(255, 196, 196)",
            "type" : [
                 "normal"             
            ],
            "height" : "6' 07\"",
            "weight" : "287.7 lbs",
            "abilities" : [
                "Truant"
            ],
            "stats" : {
                "hp" : 150,
                "attack" : 160,
                "defense" : 100,
                "sp.atk" : 95,
                "sp.def" : 65,
                "speed" : 100,
                "total" : 565
            },
             "evolution" : [
                 "Slakoth",
                 "Vigoroth",
                 "Slaking"
               ]
        },
        {
            "name" : "Nincada",
            "number" : "290",
            "sprite" : "https://raw.githubusercontent.com/PokeAPI/sprites/master/sprites/pokemon/290.png",
            "color" : "rgb(255, 196, 196)",
            "type" : [
                 "bug",
                 "ground"             
            ],
            "height" : "1' 08\"",
            "weight" : "12.1 lbs",
            "abilities" : [
                "Compound Eyes",
                "Run Away"
            ],
            "stats" : {
                "hp" : 31,
                "attack" : 45,
                "defense" : 90,
                "sp.atk" : 30,
                "sp.def" : 30,
                "speed" : 40,
                "total" : 285
            },
             "evolution" : [
                 "Nincada",
                 "Ninjask",
                 "Shedinja"
               ]
        },
        {
            "name" : "Ninjask",
            "number" : "291",
            "sprite" : "https://raw.githubusercontent.com/PokeAPI/sprites/master/sprites/pokemon/291.png",
            "color" : "rgb(255, 196, 196)",
            "type" : [
                 "bug",
                 "flying"             
            ],
            "height" : "2' 07\"",
            "weight" : "26.5 lbs",
            "abilities" : [
                "Speed Boost"
            ],
            "stats" : {
                "hp" : 61,
                "attack" : 90,
                "defense" : 45,
                "sp.atk" : 50,
                "sp.def" : 50,
                "speed" : 160,
                "total" : 435
            },
             "evolution" : [
                 "Nincada",
                 "Ninjask",
                 "Shedinja"
               ]

        },
        {
            "name" : "Shedinja",
            "number" : "292",
            "sprite" : "https://raw.githubusercontent.com/PokeAPI/sprites/master/sprites/pokemon/292.png",
            "color" : "rgb(255, 196, 196)",
            "type" : [
                 "bug",
                 "ghost"             
            ],
            "height" : "2' 07\"",
            "weight" : "2.6 lbs",
            "abilities" : [
                "Wonder Guard"
            ],
            "stats" : {
                "hp" : 1,
                "attack" : 90,
                "defense" : 45,
                "sp.atk" : 30,
                "sp.def" : 30,
                "speed" : 40,
                "total" : 285
            },
             "evolution" : [
                 "Nincada",
                 "Ninjask",
                 "Shedinja"
               ]

        },
        {
            "name" : "Whismur",
            "number" : "293",
            "sprite" : "https://raw.githubusercontent.com/PokeAPI/sprites/master/sprites/pokemon/293.png",
            "color" : "rgb(255, 196, 196)",
            "type" : [
                 "normal"             
            ],
            "height" : "2' 00\"",
            "weight" : "35.9 lbs",
            "abilities" : [
                "Soundproof",
                "Rattled"
            ],
            "stats" : {
                "hp" : 64,
                "attack" : 51,
                "defense" : 23,
                "sp.atk" : 51,
                "sp.def" : 23,
                "speed" : 28,
                "total" : 288
            },
             "evolution" : [
                 "Whismur",
                 "Loudred",
                 "Exploud"
               ]
        },
        {
            "name" : "Loudred",
            "number" : "294",
            "sprite" : "https://raw.githubusercontent.com/PokeAPI/sprites/master/sprites/pokemon/294.png",
            "color" : "rgb(255, 196, 196)",
            "type" : [
                 "normal"             
            ],
            "height" : "3' 03\"",
            "weight" : "89.3 lbs",
            "abilities" : [
                "Soundproof",
                "Scrappy"
            ],
            "stats" : {
                "hp" : 89,
                "attack" : 63,
                "defense" : 47,
                "sp.atk" : 63,
                "sp.def" : 47,
                "speed" : 31,
                "total" : 405
            },
             "evolution" : [
                 "Whismur",
                 "Loudred",
                 "Exploud"
               ]
        },
        {
            "name" : "Exploud",
            "number" : "295",
            "sprite" : "https://raw.githubusercontent.com/PokeAPI/sprites/master/sprites/pokemon/295.png",
            "color" : "rgb(255, 196, 196)",
            "type" : [
                 "normal"             
            ],
            "height" : "4' 11\"",
            "weight" : "185.2 lbs",
            "abilities" : [
                "Soundproof",
                "Scrappy"
            ],
            "stats" : {
                "hp" : 104,
                "attack" : 91,
                "defense" : 63,
                "sp.atk" : 91,
                "sp.def" : 73,
                "speed" : 68,
                "total" : 535
            },
             "evolution" : [
                 "Whismur",
                 "Loudred",
                 "Exploud"
               ]
        },
        {
            "name" : "Makuhita",
            "number" : "296",
            "sprite" : "https://raw.githubusercontent.com/PokeAPI/sprites/master/sprites/pokemon/296.png",
            "color" : "rgb(255, 196, 196)",
            "type" : [
                 "fighting"             
            ],
            "height" : "3' 03\"",
            "weight" : "190.5 lbs",
            "abilities" : [
                "Thick Fat",
                "Guts",
                "Sheer Force"
            ],
            "stats" : {
                "hp" : 72,
                "attack" : 60,
                "defense" : 30,
                "sp.atk" : 20,
                "sp.def" : 30,
                "speed" : 25,
                "total" : 310
            },
             "evolution" : [
                 "Makuhita",
                 "Hariyama"
               ]
        },
        {
            "name" : "Hariyama",
            "number" : "297",
            "sprite" : "https://raw.githubusercontent.com/PokeAPI/sprites/master/sprites/pokemon/297.png",
            "color" : "rgb(255, 196, 196)",
            "type" : [
                 "fighting"             
            ],
            "height" : "7' 07\"",
            "weight" : "559.5 lbs",
            "abilities" : [
                "Thick Fat",
                "Guts",
                "Sheer Force"
            ],
            "stats" : {
                "hp" : 144,
                "attack" : 160,
                "defense" : 90,
                "sp.atk" : 40,
                "sp.def" : 70,
                "speed" : 45,
                "total" : 535
            },
             "evolution" : [
                 "Makuhita",
                 "Hariyama"
               ]

        },
        {
            "name" : "Azurill",
            "number" : "298",
            "sprite" : "https://raw.githubusercontent.com/PokeAPI/sprites/master/sprites/pokemon/298.png",
            "color" : "rgb(255, 196, 196)",
            "type" : [
                 "normal",
                 "fairy"             
            ],
            "height" : "0' 08\"",
            "weight" : "4.4 lbs",
            "abilities" : [
                "Thick Fat",
                "Huge Power",
                "Sap Sipper"
            ],
            "stats" : {
                "hp" : 45,
                "attack" : 20,
                "defense" : 50,
                "sp.atk" : 25,
                "sp.def" : 25,
                "speed" : 40,
                "total" : 270
            },
             "evolution" : [
                 "Azurill",
                 "Marill",
                 "Azumarill"
               ]
        },
        {
            "name" : "Nosepass",
            "number" : "299",
            "sprite" : "https://raw.githubusercontent.com/PokeAPI/sprites/master/sprites/pokemon/299.png",
            "color" : "rgb(255, 196, 196)",
            "type" : [
                 "rock"             
            ],
            "height" : "3'03\"",
            "weight" : "213.8 lbs",
            "abilities" : [
                "Sturdy",
                "Magnet Pull",
                "Sand Force"
            ],
            "stats" : {
                "hp" : 30,
                "attack" : 45,
                "defense" : 135,
                "sp.atk" : 45,
                "sp.def" : 90,
                "speed" : 35,
                "total" : 435
            },
             "evolution" : [
                 "Nosepass",
                 "Probopass"
               ]
        },
        {
            "name" : "Skitty",
            "number" : "300",
            "sprite" : "https://raw.githubusercontent.com/PokeAPI/sprites/master/sprites/pokemon/300.png",
            "color" : "rgb(255, 196, 196)",
            "type" : [
                 "normal"             
            ],
            "height" : "2' 00\"",
            "weight" : "24.3 lbs",
            "abilities" : [
                "Cute Charm",
                "Normalize",
                "Wonder Skin"
            ],
            "stats" : {
                "hp" : 50,
                "attack" : 45,
                "defense" : 45,
                "sp.atk" : 35,
                "sp.def" : 35,
                "speed" : 50,
                "total" : 300
            },
             "evolution" : [
                 "Skitty",
                 "Delcatty"
               ]

        },
        {
            "name" : "Delcatty",
            "number" : "301",
            "sprite" : "https://raw.githubusercontent.com/PokeAPI/sprites/master/sprites/pokemon/301.png",
            "color" : "rgb(255, 196, 196)",
            "type" : [
                 "normal"             
            ],
            "height" : "3'07\"",
            "weight" : "71.9 lbs",
            "abilities" : [
                "Cute Charm",
                "Normalize",
                "Wonder Skin"
            ],
            "stats" : {
                "hp" : 70,
                "attack" : 65,
                "defense" : 65,
                "sp.atk" : 55,
                "sp.def" : 55,
                "speed" : 90,
                "total" : 450
            },
             "evolution" : [
                 "Skitty",
                 "Delcatty"
               ]

        },
        {
            "name" : "Sableye",
            "number" : "302",
            "sprite" : "https://raw.githubusercontent.com/PokeAPI/sprites/master/sprites/pokemon/302.png",
            "color" : "rgb(255, 196, 196)",
            "type" : [
                 "dark",
                 "ghost"             
            ],
            "height" : "1'08\"",
            "weight" : "24.3 lbs",
            "abilities" : [
                "Keen Eye",
                "Stall",
                "Prankster"
            ],
            "stats" : {
                "hp" : 50,
                "attack" : 65,
                "defense" : 45,
                "sp.atk" : 85,
                "sp.def" : 65,
                "speed" : 65,
                "total" : 435
            },
             "evolution" : [
                 "Sableye"
               ]

        },
        {
            "name" : "Mawile",
            "number" : "303",
            "sprite" : "https://raw.githubusercontent.com/PokeAPI/sprites/master/sprites/pokemon/303.png",
            "color" : "rgb(255, 196, 196)",
            "type" : [
                 "steel",
                 "fairy"             
            ],
            "height" : "2'00\"",
            "weight" : "25.4 lbs",
            "abilities" : [
                "Hyper Cutter",
                "Intimidate",
                "Sheer Force"
            ],
            "stats" : {
                "hp" : 50,
                "attack" : 75,
                "defense" : 85,
                "sp.atk" : 55,
                "sp.def" : 65,
                "speed" : 20,
                "total" : 455
            },
             "evolution" : [
                 "Mawile"
               ]

        },
        {
            "name" : "Aron",
            "number" : "304",
            "sprite" : "https://raw.githubusercontent.com/PokeAPI/sprites/master/sprites/pokemon/304.png",
            "color" : "rgb(255, 196, 196)",
            "type" : [
                 "steel",
                 "rock"             
            ],
            "height" : "1'04\"",
            "weight" : "132.3 lbs",
            "abilities" : [
                "Sturdy",
                "Rock Head",
                "Heavy Metal"
            ],
            "stats" : {
                "hp" : 50,
                "attack" : 70,
                "defense" : 100,
                "sp.atk" : 40,
                "sp.def" : 40,
                "speed" : 30,
                "total" : 395
            },
             "evolution" : [
                 "Aron",
                 "Lairon",
                 "Aggron"
               ]


        },
        {
            "name" : "Lairon",
            "number" : "305",
            "sprite" : "https://raw.githubusercontent.com/PokeAPI/sprites/master/sprites/pokemon/305.png",
            "color" : "rgb(255, 196, 196)",
            "type" : [
                 "steel",
                 "rock"             
            ],
            "height" : "1'08\"",
            "weight" : "249.8 lbs",
            "abilities" : [
                "Sturdy",
                "Rock Head",
                "Heavy Metal"
            ],
            "stats" : {
                "hp" : 60,
                "attack" : 90,
                "defense" : 140,
                "sp.atk" : 50,
                "sp.def" : 50,
                "speed" : 40,
                "total" : 505
            },
             "evolution" : [
                 "Aron",
                 "Lairon",
                 "Aggron"
               ]
               
        },
        {
            "name" : "Aggron",
            "number" : "306",
            "sprite" : "https://raw.githubusercontent.com/PokeAPI/sprites/master/sprites/pokemon/306.png",
            "color" : "rgb(255, 196, 196)",
            "type" : [
                 "steel",
                 "rock"             
            ],
            "height" : "6'11\"",
            "weight" : "793.7 lbs",
            "abilities" : [
                "Sturdy",
                "Rock Head",
                "Heavy Metal"
            ],
            "stats" : {
                "hp" : 70,
                "attack" : 110,
                "defense" : 180,
                "sp.atk" : 60,
                "sp.def" : 60,
                "speed" : 50,
                "total" : 565
            },
            "evolution" : [
                    "Aron",
                    "Lairon",
                    "Aggron"
                ]

        },
        {
            "name" : "Meditite",
            "number" : "307",
            "sprite" : "https://raw.githubusercontent.com/PokeAPI/sprites/master/sprites/pokemon/307.png",
            "color" : "rgb(255, 196, 196)",
            "type" : [
                 "fighting",
                 "psychic"
            ],
            "height" : "2'00\"",
            "weight" : "24.7 lbs",
            "abilities" : [
                "Pure Power",
                "Telepathy",
                "Meditate"
            ],
            "stats" : {
                "hp" : 45,
                "attack" : 80,
                "defense" : 35,
                "sp.atk" : 35,
                "sp.def" : 35,
                "speed" : 35,
                "total" : 275
            },
                "evolution" : [
                    "Meditite",
                    "Medicham"
                ]
        },
        {
            "name" : "Medicham",
            "number" : "308",
            "sprite" : "https://raw.githubusercontent.com/PokeAPI/sprites/master/sprites/pokemon/308.png",
            "color" : "rgb(255, 196, 196)",
            "type" : [
                 "fighting",
                 "psychic"
            ],
            "height" : "4'03\"",
            "weight" : "69.4 lbs",
            "abilities" : [
                "Pure Power",
                "Telepathy",
                "Meditate"
            ],
            "stats" : {
                "hp" : 60,
                "attack" : 100,
                "defense" : 55,
                "sp.atk" : 70,
                "sp.def" : 55,
                "speed" : 85,
                "total" : 455
            },
            "evolution" : [
                    "Meditite",
                    "Medicham"
                ]
        },
        {
            "name" : "Electrike",
            "number" : "309",
            "sprite" : "https://raw.githubusercontent.com/PokeAPI/sprites/master/sprites/pokemon/309.png",
            "color" : "rgb(255, 196, 196)",
            "type" : [
                 "electric"
            ],
            "height" : "2'00\"",
            "weight" : "33.5 lbs",
            "abilities" : [
                "Static",
                "Lightning Rod"
            ],
            "stats" : {
                "hp" : 40,
                "attack" : 65,
                "defense" : 40,
                "sp.atk" : 60,
                "sp.def" : 40,
                "speed" : 75,
                "total" : 355
            },
            "evolution" : [
                    "Electrike",
                    "Manectric"
                ]
        },
        {
            "name" : "Manectric",
            "number" : "310",
            "sprite" : "https://raw.githubusercontent.com/PokeAPI/sprites/master/sprites/pokemon/310.png",
            "color" : "rgb(255, 196, 196)",
            "type" : [
                 "electric"
            ],
            "height" : "4'11\"",
            "weight" : "88.6 lbs",
            "abilities" : [
                "Static",
                "Lightning Rod"
            ],
            "stats" : {
                "hp" : 70,
                "attack" : 105,
                "defense" : 70,
                "sp.atk" : 100,
                "sp.def" : 70,
                "speed" : 95,
                "total" : 505
            },
            "evolution" : [
                    "Electrike",
                    "Manectric"
                ]
        },
        {
            "name" : "Plusle",
            "number" : "311",
            "sprite" : "https://raw.githubusercontent.com/PokeAPI/sprites/master/sprites/pokemon/311.png",
            "color" : "rgb(255, 196, 196)",
            "type" : [
                 "electric"
            ],
            "height" : "1'04\"",
            "weight" : "9.3 lbs",
            "abilities" : [
                "Plus"
            ],
            "stats" : {
                "hp" : 60,
                "attack" : 50,
                "defense" : 40,
                "sp.atk" : 85,
                "sp.def" : 75,
                "speed" : 95,
                "total" : 405
            },
            "evolution" : [
                    "Plusle"
                ]
        },
        {
            "name" : "Minun",
            "number" : "312",
            "sprite" : "https://raw.githubusercontent.com/PokeAPI/sprites/master/sprites/pokemon/312.png",
            "color" : "rgb(255, 196, 196)",
            "type" : [
                 "electric"
            ],
            "height" : "1'04\"",
            "weight" : "9.3 lbs",
            "abilities" : [
                "Minus"
            ],
            "stats" : {
                "hp" : 60,
                "attack" : 40,
                "defense" : 50,
                "sp.atk" : 75,
                "sp.def" : 85,
                "speed" : 95,
                "total" : 405
            },
            "evolution" : [
                    "Minun"
                ]
        },
        {
            "name" : "Volbeat",
            "number" : "313",
            "sprite" : "https://raw.githubusercontent.com/PokeAPI/sprites/master/sprites/pokemon/313.png",
            "color" : "rgb(255, 196, 196)",
            "type" : [
                 "bug"
            ],
            "height" : "2'04\"",
            "weight" : "39.0 lbs",
            "abilities" : [
                "Illuminate",
                "Swarm"
            ],
            "stats" : {
                "hp" : 65,
                "attack" : 73,
                "defense" : 55,
                "sp.atk" : 47,
                "sp.def" : 75,
                "speed" : 85,
                "total" : 405
            },
            "evolution" : [
                    "Volbeat"
                ]

        },
        {
            "name" : "Illumise",
            "number" : "314",
            "sprite" : "https://raw.githubusercontent.com/PokeAPI/sprites/master/sprites/pokemon/314.png",
            "color" : "rgb(255, 196, 196)",
            "type" : [
                 "bug"
            ],
            "height" : "2'00\"",
            "weight" : "39.0 lbs",
            "abilities" : [
                "Tinted Lens",
                "Swarm"
            ],
            "stats" : {
                "hp" : 65,
                "attack" : 47,
                "defense" : 55,
                "sp.atk" : 73,
                "sp.def" : 75,
                "speed" : 85,
                "total" : 405
            },
            "evolution" : [
                    "Illumise"
                ]
        },
        {
            "name" : "Roselia",
            "number" : "315",
            "sprite" : "https://raw.githubusercontent.com/PokeAPI/sprites/master/sprites/pokemon/315.png",
            "color" : "rgb(255, 196, 196)",
            "type" : [
                 "grass",
                 "poison"
            ],
            "height" : "1'00\"",
            "weight" : "4.4 lbs",
            "abilities" : [
                "Natural Cure",
                "Poison Point",
                "Leaf Guard"
            ],
            "stats" : {
                "hp" : 50,
                "attack" : 40,
                "defense" : 85,
                "sp.atk" : 40,
                "sp.def" : 85,
                "speed" : 75,
                "total" : 405
            },
            "evolution" : [
                "Budew",
                "Roselia",
                "Roserade"
                ]
        },
        {
            "name" : "Gulpin",
            "number" : "316",
            "sprite" : "https://raw.githubusercontent.com/PokeAPI/sprites/master/sprites/pokemon/316.png",
            "color" : "rgb(255, 196, 196)",
            "type" : [
                 "poison"
            ],
            "height" : "1'04\"",
            "weight" : "22.7 lbs",
            "abilities" : [
                "Liquid Ooze",
                "Sticky Hold"
            ],
            "stats" : {
                "hp" : 70,
                "attack" : 43,
                "defense" : 53,
                "sp.atk" : 43,
                "sp.def" : 53,
                "speed" : 40,
                "total" : 305
            },
            "evolution" : [
                    "Gulpin",
                    "Swalot"
                ]
        },
        {
            "name" : "Swalot",
            "number" : "317",
            "sprite" : "https://raw.githubusercontent.com/PokeAPI/sprites/master/sprites/pokemon/317.png",
            "color" : "rgb(255, 196, 196)",
            "type" : [
                 "poison"
            ],
            "height" : "5'07\"",
            "weight" : "176.4.0 lbs",
            "abilities" : [
                "Liquid Ooze",
                "Sticky Hold"
            ],
            "stats" : {
                "hp" : 100,
                "attack" : 73,
                "defense" : 83,
                "sp.atk" : 73,
                "sp.def" : 83,
                "speed" : 55,
                "total" : 505
            },
            "evolution" : [
                    "Gulpin",
                    "Swalot"
                ]
        },
        {
            "name" : "Carvanha",
            "number" : "318",
            "sprite" : "https://raw.githubusercontent.com/PokeAPI/sprites/master/sprites/pokemon/318.png",
            "color" : "rgb(255, 196, 196)",
            "type" : [
                 "water",
                 "dark"
            ],
            "height" : "2'07\"",
            "weight" : "49.5 lbs",
            "abilities" : [
                "Rough Skin",
                "Sniper"
            ],
            "stats" : {
                "hp" : 45,
                "attack" : 90,
                "defense" : 20,
                "sp.atk" : 65,
                "sp.def" : 20,
                "speed" : 65,
                "total" : 305
            },
            "evolution" : [
                    "Carvanha",
                    "Sharpedo"
                ]
        },
        {
            "name" : "Sharpedo",
            "number" : "319",
            "sprite" : "https://raw.githubusercontent.com/PokeAPI/sprites/master/sprites/pokemon/319.png",
            "color" : "rgb(255, 196, 196)",
            "type" : [
                 "water",
                 "dark"
            ],
            "height" : "5'11\"",
            "weight" : "195.8 lbs",
            "abilities" : [
                "Rough Skin",
                "Sniper"
            ],
            "stats" : {
                "hp" : 70,
                "attack" : 120,
                "defense" : 40,
                "sp.atk" : 95,
                "sp.def" : 40,
                "speed" : 95,
                "total" : 505
            },
            "evolution" : [
                    "Carvanha",
                    "Sharpedo"
                ]
        }

   ]
}